psonoapi/__init__.py
psonoapi/__main__.py
psonoapi/cli.py
psonoapi/datamodels.py
psonoapi/exceptions.py
psonoapi/psono.py
psonoapi/psonoapihelper.py
psonoapi/utility.py
psonoapi-0.2.5.dist-info/licenses/LICENSE
psonoapi-0.2.5.dist-info/METADATA
psonoapi-0.2.5.dist-info/WHEEL
psonoapi-0.2.5.dist-info/entry_points.txt
psonoapi-0.2.5.dist-info/top_level.txt
psonoapi-0.2.5.dist-info/RECORD
