Metadata-Version: 2.4
Name: psonoapi
Version: 0.2.5
Summary: Psono API interface for python
Author-email: Matthew Parslow <mparslow@cybersecure.com>
License-Expression: MIT
Project-URL: Homepage, https://gitlab.com/cyber-secure-public/psono-python-module
Project-URL: Issues, https://gitlab.com/cyber-secure-public/psono-python-module/-/issues
Classifier: Programming Language :: Python :: 3
Classifier: Operating System :: OS Independent
Requires-Python: >=3.9
License-File: LICENSE
Requires-Dist: pydantic
Requires-Dist: pynacl
Requires-Dist: requests
Requires-Dist: deepdiff
Requires-Dist: click
Requires-Dist: tabulate
Dynamic: license-file
